{
  "genesis_time": "2020-08-13T00:00:00.000000000Z",
  "chain_id": "pandora-1",
  "consensus_params": {
    "block": {
      "max_bytes": "22020096",
      "max_gas": "-1",
      "time_iota_ms": "1000"
    },
    "evidence": {
      "max_age": "100000"
    },
    "validator": {
      "pub_key_types": [
        "ed25519"
      ]
    }
  },
  "app_hash": "",
  "app_state": {
    "accounts": [
      {
        "account_number": "21",
        "address": "ixo1p894v8zqx427dvcdclv07lhul596pac6c5uhkt",
        "coins": [
          {
            "amount": "985435",
            "denom": "uixo"
          }
        ],
        "delegated_free": [],
        "delegated_vesting": [],
        "end_time": "0",
        "module_name": "",
        "module_permissions": null,
        "original_vesting": [],
        "sequence_number": "2",
        "start_time": "0"
      },
      {
        "account_number": "14",
        "address": "ixo1p2htd8tgsm4m22w3t94xvy09m9cadzj3kqpycw",
        "coins": [],
        "delegated_free": [],
        "delegated_vesting": [],
        "end_time": "0",
        "module_name": "bonds_mint_burn_account",
        "module_permissions": [
          "minter",
          "burner"
        ],
        "original_vesting": [],
        "sequence_number": "0",
        "start_time": "0"
      },
      {
        "account_number": "55",
        "address": "ixo1pcl6x7j39xcnzhrhp83ta335acxqpnaduxw383",
        "coins": [],
        "delegated_free": [],
        "delegated_vesting": [],
        "end_time": "0",
        "module_name": "",
        "module_permissions": null,
        "original_vesting": [],
        "sequence_number": "0",
        "start_time": "0"
      },
      {
        "account_number": "16",
        "address": "ixo1zjfd9czp9249yq6gxlh23l8heqdkwwhh97zlj2",
        "coins": [
          {
            "amount": "12",
            "denom": "res"
          }
        ],
        "delegated_free": [],
        "delegated_vesting": [],
        "end_time": "0",
        "module_name": "",
        "module_permissions": null,
        "original_vesting": [],
        "sequence_number": "0",
        "start_time": "0"
      },
      {
        "account_number": "32",
        "address": "ixo1zmxa64sj7e7zs5pfuavy83dxkzmfy3jk29h8ye",
        "coins": [],
        "delegated_free": [],
        "delegated_vesting": [],
        "end_time": "0",
        "module_name": "",
        "module_permissions": null,
        "original_vesting": [],
        "sequence_number": "0",
        "start_time": "0"
      },
      {
        "account_number": "0",
        "address": "ixo1z7vwqeku3sz34sd8eq4ppg9stkv8ugu959jy26",
        "coins": [
          {
            "amount": "860000",
            "denom": "res"
          },
          {
            "amount": "860000",
            "denom": "rez"
          },
          {
            "amount": "99946205725",
            "denom": "uixo"
          }
        ],
        "delegated_free": [],
        "delegated_vesting": [],
        "end_time": "0",
        "module_name": "",
        "module_permissions": null,
        "original_vesting": [],
        "sequence_number": "7",
        "start_time": "0"
      },
      {
        "account_number": "54",
        "address": "ixo1yq3jv9fvq9azpt6xsqlf3vnfcw32s8jtx57vjt",
        "coins": [],
        "delegated_free": [],
        "delegated_vesting": [],
        "end_time": "0",
        "module_name": "",
        "module_permissions": null,
        "original_vesting": [],
        "sequence_number": "0",
        "start_time": "0"
      },
      {
        "account_number": "61",
        "address": "ixo1y8d0vq2vdlcwkc69u56jm7mtq0ukmurldjhznm",
        "coins": [],
        "delegated_free": [],
        "delegated_vesting": [],
        "end_time": "0",
        "module_name": "",
        "module_permissions": null,
        "original_vesting": [],
        "sequence_number": "0",
        "start_time": "0"
      },
      {
        "account_number": "20",
        "address": "ixo19h3lqj50uhzdrv8mkafnp55nqmz4ghc2sd3m48",
        "coins": [
          {
            "amount": "39533",
            "denom": "res"
          },
          {
            "amount": "40000",
            "denom": "rez"
          },
          {
            "amount": "1",
            "denom": "token1"
          },
          {
            "amount": "36992527",
            "denom": "uixo"
          },
          {
            "amount": "2000000000",
            "denom": "xusd"
          }
        ],
        "delegated_free": [],
        "delegated_vesting": [],
        "end_time": "0",
        "module_name": "",
        "module_permissions": null,
        "original_vesting": [],
        "sequence_number": "4",
        "start_time": "0"
      },
      {
        "account_number": "49",
        "address": "ixo1xhhrdefx005zc79hjptafsjnf70ud2ef2ylp4d",
        "coins": [],
        "delegated_free": [],
        "delegated_vesting": [],
        "end_time": "0",
        "module_name": "",
        "module_permissions": null,
        "original_vesting": [],
        "sequence_number": "0",
        "start_time": "0"
      },
      {
        "account_number": "43",
        "address": "ixo18z5jl6ufalekv3sp4pkrqej0nxurszke29xwkm",
        "coins": [],
        "delegated_free": [],
        "delegated_vesting": [],
        "end_time": "0",
        "module_name": "",
        "module_permissions": null,
        "original_vesting": [],
        "sequence_number": "0",
        "start_time": "0"
      },
      {
        "account_number": "38",
        "address": "ixo18sfltmqgw68xydhnd5r024xl2pk5anpyjann0a",
        "coins": [],
        "delegated_free": [],
        "delegated_vesting": [],
        "end_time": "0",
        "module_name": "",
        "module_permissions": null,
        "original_vesting": [],
        "sequence_number": "0",
        "start_time": "0"
      },
      {
        "account_number": "13",
        "address": "ixo18uhrv69d6xvhn3a0pdgcftuq3g2txplpptqyzc",
        "coins": [],
        "delegated_free": [],
        "delegated_vesting": [],
        "end_time": "0",
        "module_name": "batches_intermediary_account",
        "module_permissions": null,
        "original_vesting": [],
        "sequence_number": "0",
        "start_time": "0"
      },
      {
        "account_number": "45",
        "address": "ixo1874tk9p72huycxesc4euceuzygf9t9qrnerzpy",
        "coins": [
          {
            "amount": "985438",
            "denom": "uixo"
          }
        ],
        "delegated_free": [],
        "delegated_vesting": [],
        "end_time": "0",
        "module_name": "",
        "module_permissions": null,
        "original_vesting": [],
        "sequence_number": "2",
        "start_time": "0"
      },
      {
        "account_number": "23",
        "address": "ixo1f2p6nlkn0txhfj3pd6el5clfrvcpxsjdvyrd8y",
        "coins": [],
        "delegated_free": [],
        "delegated_vesting": [],
        "end_time": "0",
        "module_name": "",
        "module_permissions": null,
        "original_vesting": [],
        "sequence_number": "0",
        "start_time": "0"
      },
      {
        "account_number": "1",
        "address": "ixo1f0sldkez5kdw6sdm2yrw9dkufeq6trc3a6ngce",
        "coins": [
          {
            "amount": "900000",
            "denom": "res"
          },
          {
            "amount": "900000",
            "denom": "rez"
          },
          {
            "amount": "99989998750",
            "denom": "uixo"
          }
        ],
        "delegated_free": [],
        "delegated_vesting": [],
        "end_time": "0",
        "module_name": "",
        "module_permissions": null,
        "original_vesting": [],
        "sequence_number": "1",
        "start_time": "0"
      },
      {
        "account_number": "42",
        "address": "ixo1f7f6ntaqhh47gd34xh8q5dma5uq7dxufzmyxcl",
        "coins": [],
        "delegated_free": [],
        "delegated_vesting": [],
        "end_time": "0",
        "module_name": "",
        "module_permissions": null,
        "original_vesting": [],
        "sequence_number": "0",
        "start_time": "0"
      },
      {
        "account_number": "7",
        "address": "ixo1fl48vsnmsdzcv85q5d2q4z5ajdha8yu32whaay",
        "coins": [
          {
            "amount": "1000000",
            "denom": "uixo"
          }
        ],
        "delegated_free": [],
        "delegated_vesting": [],
        "end_time": "0",
        "module_name": "bonded_tokens_pool",
        "module_permissions": [
          "burner",
          "staking"
        ],
        "original_vesting": [],
        "sequence_number": "0",
        "start_time": "0"
      },
      {
        "account_number": "59",
        "address": "ixo12rdzv9jj2qqtu7m9jc8q4rl4vthp7wz4m2qu74",
        "coins": [
          {
            "amount": "984486",
            "denom": "uixo"
          }
        ],
        "delegated_free": [],
        "delegated_vesting": [],
        "end_time": "0",
        "module_name": "",
        "module_permissions": null,
        "original_vesting": [],
        "sequence_number": "2",
        "start_time": "0"
      },
      {
        "account_number": "39",
        "address": "ixo128lfrvlerf9dwh6shwp75y7drrz0tnq43st8qw",
        "coins": [
          {
            "amount": "985435",
            "denom": "uixo"
          }
        ],
        "delegated_free": [],
        "delegated_vesting": [],
        "end_time": "0",
        "module_name": "",
        "module_permissions": null,
        "original_vesting": [],
        "sequence_number": "2",
        "start_time": "0"
      },
      {
        "account_number": "8",
        "address": "ixo1tygms3xhhs3yv487phx3dw4a95jn7t7l7wtvts",
        "coins": [],
        "delegated_free": [],
        "delegated_vesting": [],
        "end_time": "0",
        "module_name": "not_bonded_tokens_pool",
        "module_permissions": [
          "burner",
          "staking"
        ],
        "original_vesting": [],
        "sequence_number": "0",
        "start_time": "0"
      },
      {
        "account_number": "24",
        "address": "ixo1v22htx9j4vz0jxpun20nhl785mh0wcmatrrxku",
        "coins": [],
        "delegated_free": [],
        "delegated_vesting": [],
        "end_time": "0",
        "module_name": "",
        "module_permissions": null,
        "original_vesting": [],
        "sequence_number": "0",
        "start_time": "0"
      },
      {
        "account_number": "40",
        "address": "ixo1v67krkrlxvj3sumghaqygftv7dprd4lx3sxmpq",
        "coins": [],
        "delegated_free": [],
        "delegated_vesting": [],
        "end_time": "0",
        "module_name": "",
        "module_permissions": null,
        "original_vesting": [],
        "sequence_number": "0",
        "start_time": "0"
      },
      {
        "account_number": "12",
        "address": "ixo1vmafl8f3s6uuzwnxkqz0eza47v6ecn0tk4a2md",
        "coins": [],
        "delegated_free": [],
        "delegated_vesting": [],
        "end_time": "0",
        "module_name": "treasury",
        "module_permissions": [
          "minter",
          "burner"
        ],
        "original_vesting": [],
        "sequence_number": "0",
        "start_time": "0"
      },
      {
        "account_number": "41",
        "address": "ixo1djw3hrjwv66phfhtagywceru8qjy480r9ay0yz",
        "coins": [],
        "delegated_free": [],
        "delegated_vesting": [],
        "end_time": "0",
        "module_name": "",
        "module_permissions": null,
        "original_vesting": [],
        "sequence_number": "0",
        "start_time": "0"
      },
      {
        "account_number": "44",
        "address": "ixo1djwl96r7gqfx5h3njt8u6ezx5qqtx9k78yry3f",
        "coins": [],
        "delegated_free": [],
        "delegated_vesting": [],
        "end_time": "0",
        "module_name": "",
        "module_permissions": null,
        "original_vesting": [],
        "sequence_number": "0",
        "start_time": "0"
      },
      {
        "account_number": "53",
        "address": "ixo1d59yugmejpt9h86qu0f7samaapxlk74fvfqhp6",
        "coins": [],
        "delegated_free": [],
        "delegated_vesting": [],
        "end_time": "0",
        "module_name": "",
        "module_permissions": null,
        "original_vesting": [],
        "sequence_number": "0",
        "start_time": "0"
      },
      {
        "account_number": "5",
        "address": "ixo1d5u5ta7np7vefxa7ttpuy5aurg7q5regm0t2un",
        "coins": [
          {
            "amount": "999900",
            "denom": "res"
          },
          {
            "amount": "999900",
            "denom": "rez"
          },
          {
            "amount": "5",
            "denom": "token3"
          },
          {
            "amount": "99999990000",
            "denom": "uixo"
          }
        ],
        "delegated_free": [],
        "delegated_vesting": [],
        "end_time": "0",
        "module_name": "",
        "module_permissions": null,
        "original_vesting": [],
        "sequence_number": "2",
        "start_time": "0"
      },
      {
        "account_number": "60",
        "address": "ixo1d6jhc4fkxfpfrj2am946rjwyzs3gr9f4a53rnt",
        "coins": [],
        "delegated_free": [],
        "delegated_vesting": [],
        "end_time": "0",
        "module_name": "",
        "module_permissions": null,
        "original_vesting": [],
        "sequence_number": "0",
        "start_time": "0"
      },
      {
        "account_number": "35",
        "address": "ixo102jkxgp6za7u5582q6ja6kn6j5t622rur9930e",
        "coins": [],
        "delegated_free": [],
        "delegated_vesting": [],
        "end_time": "0",
        "module_name": "",
        "module_permissions": null,
        "original_vesting": [],
        "sequence_number": "0",
        "start_time": "0"
      },
      {
        "account_number": "9",
        "address": "ixo10d07y265gmmuvt4z0w9aw880jnsr700j9hdhjq",
        "coins": [],
        "delegated_free": [],
        "delegated_vesting": [],
        "end_time": "0",
        "module_name": "gov",
        "module_permissions": [
          "burner"
        ],
        "original_vesting": [],
        "sequence_number": "0",
        "start_time": "0"
      },
      {
        "account_number": "27",
        "address": "ixo105zmxjr9zmv4nrudh00pwt6ntqa9v08vrk05ny",
        "coins": [
          {
            "amount": "985435",
            "denom": "uixo"
          }
        ],
        "delegated_free": [],
        "delegated_vesting": [],
        "end_time": "0",
        "module_name": "",
        "module_permissions": null,
        "original_vesting": [],
        "sequence_number": "2",
        "start_time": "0"
      },
      {
        "account_number": "3",
        "address": "ixo107pmtx9wyndup8f9lgj6d7dnfq5kuf3sapg0vx",
        "coins": [
          {
            "amount": "986490",
            "denom": "res"
          },
          {
            "amount": "1000000",
            "denom": "rez"
          },
          {
            "amount": "3",
            "denom": "token1"
          },
          {
            "amount": "3",
            "denom": "token2"
          },
          {
            "amount": "5",
            "denom": "token4"
          },
          {
            "amount": "99999956000",
            "denom": "uixo"
          }
        ],
        "delegated_free": [],
        "delegated_vesting": [],
        "end_time": "0",
        "module_name": "",
        "module_permissions": null,
        "original_vesting": [],
        "sequence_number": "9",
        "start_time": "0"
      },
      {
        "account_number": "25",
        "address": "ixo1s9nshrjd968qg25phucwf98vg0krjh5vjvuhup",
        "coins": [],
        "delegated_free": [],
        "delegated_vesting": [],
        "end_time": "0",
        "module_name": "",
        "module_permissions": null,
        "original_vesting": [],
        "sequence_number": "0",
        "start_time": "0"
      },
      {
        "account_number": "64",
        "address": "ixo1s0vcxa7jh324aggczgtzs7vesnvtarpal4r55n",
        "coins": [],
        "delegated_free": [],
        "delegated_vesting": [],
        "end_time": "0",
        "module_name": "",
        "module_permissions": null,
        "original_vesting": [],
        "sequence_number": "0",
        "start_time": "0"
      },
      {
        "account_number": "19",
        "address": "ixo1s5jjwylnzj6twze5asnj5vl92xszm65jeps5aw",
        "coins": [
          {
            "amount": "2",
            "denom": "token1"
          },
          {
            "amount": "2",
            "denom": "token2"
          }
        ],
        "delegated_free": [],
        "delegated_vesting": [],
        "end_time": "0",
        "module_name": "",
        "module_permissions": null,
        "original_vesting": [],
        "sequence_number": "0",
        "start_time": "0"
      },
      {
        "account_number": "58",
        "address": "ixo13t4ppcgznzny5swf597chk7rtm4x974l33tt8d",
        "coins": [
          {
            "amount": "99388",
            "denom": "res"
          },
          {
            "amount": "100000",
            "denom": "rez"
          },
          {
            "amount": "1",
            "denom": "token1"
          },
          {
            "amount": "9994837",
            "denom": "uixo"
          },
          {
            "amount": "2000000000",
            "denom": "xusd"
          }
        ],
        "delegated_free": [],
        "delegated_vesting": [],
        "end_time": "0",
        "module_name": "",
        "module_permissions": null,
        "original_vesting": [],
        "sequence_number": "2",
        "start_time": "0"
      },
      {
        "account_number": "15",
        "address": "ixo1jqx44zqeyzhjzpp6xa2uxe0clgx4hfwpqeh96e",
        "coins": [
          {
            "amount": "2072",
            "denom": "res"
          }
        ],
        "delegated_free": [],
        "delegated_vesting": [],
        "end_time": "0",
        "module_name": "",
        "module_permissions": null,
        "original_vesting": [],
        "sequence_number": "0",
        "start_time": "0"
      },
      {
        "account_number": "46",
        "address": "ixo1jv59h24f2l4dc4uynpcz6nek6l4a3ph4w8gdel",
        "coins": [],
        "delegated_free": [],
        "delegated_vesting": [],
        "end_time": "0",
        "module_name": "",
        "module_permissions": null,
        "original_vesting": [],
        "sequence_number": "0",
        "start_time": "0"
      },
      {
        "account_number": "6",
        "address": "ixo1jv65s3grqf6v6jl3dp4t6c9t9rk99cd8c26wdv",
        "coins": [
          {
            "amount": "4351",
            "denom": "uixo"
          }
        ],
        "delegated_free": [],
        "delegated_vesting": [],
        "end_time": "0",
        "module_name": "distribution",
        "module_permissions": null,
        "original_vesting": [],
        "sequence_number": "0",
        "start_time": "0"
      },
      {
        "account_number": "29",
        "address": "ixo1j6asna38vta9t4ugata64vvutwnwyuw28mwyqn",
        "coins": [],
        "delegated_free": [],
        "delegated_vesting": [],
        "end_time": "0",
        "module_name": "",
        "module_permissions": null,
        "original_vesting": [],
        "sequence_number": "0",
        "start_time": "0"
      },
      {
        "account_number": "2",
        "address": "ixo15keecfh97jhcsvxdlp8rgtcq4uuhvl4kw5y7qq",
        "coins": [
          {
            "amount": "1000000",
            "denom": "res"
          },
          {
            "amount": "1000000",
            "denom": "rez"
          },
          {
            "amount": "100000000000",
            "denom": "uixo"
          }
        ],
        "delegated_free": [],
        "delegated_vesting": [],
        "end_time": "0",
        "module_name": "",
        "module_permissions": null,
        "original_vesting": [],
        "sequence_number": "0",
        "start_time": "0"
      },
      {
        "account_number": "63",
        "address": "ixo145p7whcq5a7ryp08dnt6k2j6uta8uurta8tmtl",
        "coins": [],
        "delegated_free": [],
        "delegated_vesting": [],
        "end_time": "0",
        "module_name": "",
        "module_permissions": null,
        "original_vesting": [],
        "sequence_number": "0",
        "start_time": "0"
      },
      {
        "account_number": "34",
        "address": "ixo14a93em9gcyw3j6ah5lxw2e9gr8y7g7armxq4vn",
        "coins": [],
        "delegated_free": [],
        "delegated_vesting": [],
        "end_time": "0",
        "module_name": "",
        "module_permissions": null,
        "original_vesting": [],
        "sequence_number": "0",
        "start_time": "0"
      },
      {
        "account_number": "22",
        "address": "ixo1kgdjfmy9xh53j35khxf7yhln9q57sch35dtxxe",
        "coins": [],
        "delegated_free": [],
        "delegated_vesting": [],
        "end_time": "0",
        "module_name": "",
        "module_permissions": null,
        "original_vesting": [],
        "sequence_number": "0",
        "start_time": "0"
      },
      {
        "account_number": "57",
        "address": "ixo1kugfy5k2hl640eetpch0szcetankknj8zptjes",
        "coins": [
          {
            "amount": "100000",
            "denom": "res"
          },
          {
            "amount": "100000",
            "denom": "rez"
          },
          {
            "amount": "10000000",
            "denom": "uixo"
          },
          {
            "amount": "1000000000",
            "denom": "xusd"
          }
        ],
        "delegated_free": [],
        "delegated_vesting": [],
        "end_time": "0",
        "module_name": "",
        "module_permissions": null,
        "original_vesting": [],
        "sequence_number": "0",
        "start_time": "0"
      },
      {
        "account_number": "62",
        "address": "ixo1h0yfg4hwr94hnjefqtt7gtx7kwf7t074zx7z2j",
        "coins": [],
        "delegated_free": [],
        "delegated_vesting": [],
        "end_time": "0",
        "module_name": "",
        "module_permissions": null,
        "original_vesting": [],
        "sequence_number": "0",
        "start_time": "0"
      },
      {
        "account_number": "4",
        "address": "ixo1cpa6w2wnqyxpxm4rryfjwjnx75kn4xt372dp3y",
        "coins": [
          {
            "amount": "987495",
            "denom": "res"
          },
          {
            "amount": "1000000",
            "denom": "rez"
          },
          {
            "amount": "5",
            "denom": "token2"
          },
          {
            "amount": "99999966450",
            "denom": "uixo"
          }
        ],
        "delegated_free": [],
        "delegated_vesting": [],
        "end_time": "0",
        "module_name": "",
        "module_permissions": null,
        "original_vesting": [],
        "sequence_number": "14",
        "start_time": "0"
      },
      {
        "account_number": "26",
        "address": "ixo1cgxcumdjcsswldyjnuvgrau7526r5h2mnl2kw6",
        "coins": [],
        "delegated_free": [],
        "delegated_vesting": [],
        "end_time": "0",
        "module_name": "",
        "module_permissions": null,
        "original_vesting": [],
        "sequence_number": "0",
        "start_time": "0"
      },
      {
        "account_number": "52",
        "address": "ixo1csetxz40p695pkt0rws5vw8z87lmphvq28wg5f",
        "coins": [],
        "delegated_free": [],
        "delegated_vesting": [],
        "end_time": "0",
        "module_name": "",
        "module_permissions": null,
        "original_vesting": [],
        "sequence_number": "0",
        "start_time": "0"
      },
      {
        "account_number": "31",
        "address": "ixo1eykltnkjph2vm90gqak57drwyehq5pypvsd7pm",
        "coins": [],
        "delegated_free": [],
        "delegated_vesting": [],
        "end_time": "0",
        "module_name": "",
        "module_permissions": null,
        "original_vesting": [],
        "sequence_number": "0",
        "start_time": "0"
      },
      {
        "account_number": "56",
        "address": "ixo16z8pc6jxelx00ep8jejxv4p8ee27k0w6ku4env",
        "coins": [],
        "delegated_free": [],
        "delegated_vesting": [],
        "end_time": "0",
        "module_name": "",
        "module_permissions": null,
        "original_vesting": [],
        "sequence_number": "0",
        "start_time": "0"
      },
      {
        "account_number": "48",
        "address": "ixo168t3wrwl5tehj8pmhnv4wl76qagdtlcrf0lczn",
        "coins": [],
        "delegated_free": [],
        "delegated_vesting": [],
        "end_time": "0",
        "module_name": "",
        "module_permissions": null,
        "original_vesting": [],
        "sequence_number": "0",
        "start_time": "0"
      },
      {
        "account_number": "18",
        "address": "ixo16k5rk8eu4gsg4xwz7stuns83zgugem3zt84hrw",
        "coins": [
          {
            "amount": "25010",
            "denom": "res"
          }
        ],
        "delegated_free": [],
        "delegated_vesting": [],
        "end_time": "0",
        "module_name": "",
        "module_permissions": null,
        "original_vesting": [],
        "sequence_number": "0",
        "start_time": "0"
      },
      {
        "account_number": "10",
        "address": "ixo1m3h30wlvsf8llruxtpukdvsy0km2kum8hye2rn",
        "coins": [],
        "delegated_free": [],
        "delegated_vesting": [],
        "end_time": "0",
        "module_name": "mint",
        "module_permissions": [
          "minter"
        ],
        "original_vesting": [],
        "sequence_number": "0",
        "start_time": "0"
      },
      {
        "account_number": "33",
        "address": "ixo1mka962rlp4ndtj7tu6kd3749l5ppuqwc9ncdd0",
        "coins": [
          {
            "amount": "979698",
            "denom": "uixo"
          }
        ],
        "delegated_free": [],
        "delegated_vesting": [],
        "end_time": "0",
        "module_name": "",
        "module_permissions": null,
        "original_vesting": [],
        "sequence_number": "2",
        "start_time": "0"
      },
      {
        "account_number": "36",
        "address": "ixo1mc26j5u0mzezvn0y39vuh07y7zhcwk70lvw9f5",
        "coins": [],
        "delegated_free": [],
        "delegated_vesting": [],
        "end_time": "0",
        "module_name": "",
        "module_permissions": null,
        "original_vesting": [],
        "sequence_number": "0",
        "start_time": "0"
      },
      {
        "account_number": "37",
        "address": "ixo1meqgeyxr0cvpe3lmajsvj89ahrl4qzqy9sa7hp",
        "coins": [],
        "delegated_free": [],
        "delegated_vesting": [],
        "end_time": "0",
        "module_name": "",
        "module_permissions": null,
        "original_vesting": [],
        "sequence_number": "0",
        "start_time": "0"
      },
      {
        "account_number": "30",
        "address": "ixo1uzyy4u5vmcq69r356ux2ay28rkqt3rmte7gp79",
        "coins": [],
        "delegated_free": [],
        "delegated_vesting": [],
        "end_time": "0",
        "module_name": "",
        "module_permissions": null,
        "original_vesting": [],
        "sequence_number": "0",
        "start_time": "0"
      },
      {
        "account_number": "28",
        "address": "ixo1anflsj7xpnenlervqgneexwmnc89uq7kc45754",
        "coins": [],
        "delegated_free": [],
        "delegated_vesting": [],
        "end_time": "0",
        "module_name": "",
        "module_permissions": null,
        "original_vesting": [],
        "sequence_number": "0",
        "start_time": "0"
      },
      {
        "account_number": "11",
        "address": "ixo17xpfvakm2amg962yls6f84z3kell8c5l0vaj0w",
        "coins": [],
        "delegated_free": [],
        "delegated_vesting": [],
        "end_time": "0",
        "module_name": "fee_collector",
        "module_permissions": null,
        "original_vesting": [],
        "sequence_number": "0",
        "start_time": "0"
      },
      {
        "account_number": "50",
        "address": "ixo175l89h7ljfyh5l6xssqtlnfwyx26zvj7a7q5de",
        "coins": [],
        "delegated_free": [],
        "delegated_vesting": [],
        "end_time": "0",
        "module_name": "",
        "module_permissions": null,
        "original_vesting": [],
        "sequence_number": "0",
        "start_time": "0"
      },
      {
        "account_number": "51",
        "address": "ixo177zujyz2zn2upaj089lxwn3l5x9pj4r420457y",
        "coins": [
          {
            "amount": "985433",
            "denom": "uixo"
          }
        ],
        "delegated_free": [],
        "delegated_vesting": [],
        "end_time": "0",
        "module_name": "",
        "module_permissions": null,
        "original_vesting": [],
        "sequence_number": "2",
        "start_time": "0"
      },
      {
        "account_number": "47",
        "address": "ixo1lfsthzhftu6wdxcl3adtkagn378g8rcpn5u65a",
        "coins": [],
        "delegated_free": [],
        "delegated_vesting": [],
        "end_time": "0",
        "module_name": "",
        "module_permissions": null,
        "original_vesting": [],
        "sequence_number": "0",
        "start_time": "0"
      },
      {
        "account_number": "17",
        "address": "ixo1l0nklpu8fqy9tce8c4ud5tas49vh9anwgy69vl",
        "coins": [
          {
            "amount": "100",
            "denom": "res"
          },
          {
            "amount": "100",
            "denom": "rez"
          }
        ],
        "delegated_free": [],
        "delegated_vesting": [],
        "end_time": "0",
        "module_name": "",
        "module_permissions": null,
        "original_vesting": [],
        "sequence_number": "0",
        "start_time": "0"
      }
    ],
    "auth": {
      "params": {
        "max_memo_characters": "256",
        "sig_verify_cost_ed25519": "590",
        "sig_verify_cost_secp256k1": "1000",
        "tx_sig_limit": "7",
        "tx_size_cost_per_byte": "10"
      }
    },
    "bank": {
      "send_enabled": true
    },
    "bonds": {
      "batches": [
        {
          "blocks_remaining": "2",
          "bond_did": "did:ixo:48PVm1uyF6QVDSPdGRWw4T",
          "buy_prices": null,
          "buys": null,
          "sell_prices": null,
          "sells": null,
          "swaps": null,
          "total_buy_amount": {
            "amount": "0",
            "denom": "token3"
          },
          "total_sell_amount": {
            "amount": "0",
            "denom": "token3"
          }
        },
        {
          "blocks_remaining": "2",
          "bond_did": "did:ixo:JHcN95bkS4aAWk3TKXapA2",
          "buy_prices": null,
          "buys": null,
          "sell_prices": null,
          "sells": null,
          "swaps": null,
          "total_buy_amount": {
            "amount": "0",
            "denom": "token2"
          },
          "total_sell_amount": {
            "amount": "0",
            "denom": "token2"
          }
        },
        {
          "blocks_remaining": "1",
          "bond_did": "did:ixo:RYLHkfNpbA8Losy68jt4yF",
          "buy_prices": null,
          "buys": null,
          "sell_prices": null,
          "sells": null,
          "swaps": null,
          "total_buy_amount": {
            "amount": "0",
            "denom": "token4"
          },
          "total_sell_amount": {
            "amount": "0",
            "denom": "token4"
          }
        },
        {
          "blocks_remaining": "1",
          "bond_did": "did:ixo:U7GK8p8rVhJMKhBVRCJJ8c",
          "buy_prices": null,
          "buys": null,
          "sell_prices": null,
          "sells": null,
          "swaps": null,
          "total_buy_amount": {
            "amount": "0",
            "denom": "token1"
          },
          "total_sell_amount": {
            "amount": "0",
            "denom": "token1"
          }
        }
      ],
      "bonds": [
        {
          "state": "OPEN",
          "outcome_payment": [],
          "allow_sells": true,
          "batch_blocks": "2",
          "bond_did": "did:ixo:48PVm1uyF6QVDSPdGRWw4T",
          "creator_did": "did:ixo:4XJLBfGtWSGKSz4BeRxdun",
          "current_supply": {
            "amount": "5",
            "denom": "token3"
          },
          "description": "Swapper function between res and rez",
          "exit_fee_percentage": "0.000000000000000000",
          "fee_address": "ixo18z0n9vxjxg6u6dpg4jhnh52fw46n7nedca5lgg",
          "function_parameters": null,
          "function_type": "swapper_function",
          "max_supply": {
            "amount": "1000000",
            "denom": "token3"
          },
          "name": "Test Token 3",
          "order_quantity_limits": [],
          "reserve_address": "ixo1l0nklpu8fqy9tce8c4ud5tas49vh9anwgy69vl",
          "reserve_tokens": [
            "res",
            "rez"
          ],
          "sanity_margin_percentage": "0.000000000000000000",
          "sanity_rate": "0.000000000000000000",
          "token": "token3",
          "tx_fee_percentage": "0.000000000000000000"
        },
        {
          "state": "OPEN",
          "outcome_payment": [],
          "allow_sells": true,
          "batch_blocks": "3",
          "bond_did": "did:ixo:JHcN95bkS4aAWk3TKXapA2",
          "creator_did": "did:ixo:4XJLBfGtWSGKSz4BeRxdun",
          "current_supply": {
            "amount": "10",
            "denom": "token2"
          },
          "description": "Power function with zero fees and batch_blocks=4",
          "exit_fee_percentage": "0.000000000000000000",
          "fee_address": "ixo165df9astyzyqqzkv6mw0fuzadt6q752zfed9an",
          "function_parameters": [
            {
              "param": "m",
              "value": "10"
            },
            {
              "param": "n",
              "value": "3"
            },
            {
              "param": "c",
              "value": "1"
            }
          ],
          "function_type": "power_function",
          "max_supply": {
            "amount": "1000000",
            "denom": "token2"
          },
          "name": "Test Token 2",
          "order_quantity_limits": [],
          "reserve_address": "ixo16k5rk8eu4gsg4xwz7stuns83zgugem3zt84hrw",
          "reserve_tokens": [
            "res"
          ],
          "sanity_margin_percentage": "0.000000000000000000",
          "sanity_rate": "0.000000000000000000",
          "token": "token2",
          "tx_fee_percentage": "0.000000000000000000"
        },
        {
          "state": "OPEN",
          "outcome_payment": [],
          "allow_sells": true,
          "batch_blocks": "1",
          "bond_did": "did:ixo:RYLHkfNpbA8Losy68jt4yF",
          "creator_did": "did:ixo:4XJLBfGtWSGKSz4BeRxdun",
          "current_supply": {
            "amount": "5",
            "denom": "token4"
          },
          "description": "Swapper function between res and rez",
          "exit_fee_percentage": "5.000000000000000000",
          "fee_address": "ixo14fzpuyvqjwjpt4vwphv3e6v9leg9uxkklqh892",
          "function_parameters": null,
          "function_type": "swapper_function",
          "max_supply": {
            "amount": "1000000",
            "denom": "token4"
          },
          "name": "Test Token 4",
          "order_quantity_limits": [],
          "reserve_address": "ixo1s5jjwylnzj6twze5asnj5vl92xszm65jeps5aw",
          "reserve_tokens": [
            "token1",
            "token2"
          ],
          "sanity_margin_percentage": "0.000000000000000000",
          "sanity_rate": "0.000000000000000000",
          "token": "token4",
          "tx_fee_percentage": "2.500000000000000000"
        },
        {
          "state": "OPEN",
          "outcome_payment": [],
          "allow_sells": true,
          "batch_blocks": "1",
          "bond_did": "did:ixo:U7GK8p8rVhJMKhBVRCJJ8c",
          "creator_did": "did:ixo:4XJLBfGtWSGKSz4BeRxdun",
          "current_supply": {
            "amount": "7",
            "denom": "token1"
          },
          "description": "Power function with non-zero fees and batch_blocks=1",
          "exit_fee_percentage": "0.100000000000000000",
          "fee_address": "ixo1zjfd9czp9249yq6gxlh23l8heqdkwwhh97zlj2",
          "function_parameters": [
            {
              "param": "m",
              "value": "12"
            },
            {
              "param": "n",
              "value": "2"
            },
            {
              "param": "c",
              "value": "100"
            }
          ],
          "function_type": "power_function",
          "max_supply": {
            "amount": "1000000",
            "denom": "token1"
          },
          "name": "Test Token 1",
          "order_quantity_limits": [],
          "reserve_address": "ixo1jqx44zqeyzhjzpp6xa2uxe0clgx4hfwpqeh96e",
          "reserve_tokens": [
            "res"
          ],
          "sanity_margin_percentage": "0.000000000000000000",
          "sanity_rate": "0.000000000000000000",
          "token": "token1",
          "tx_fee_percentage": "0.500000000000000000"
        }
      ]
    },
    "crisis": {
      "constant_fee": {
        "amount": "1000",
        "denom": "uixo"
      }
    },
    "did": {
      "did_docs": [
        {
          "type": "did/BaseDidDoc",
          "value": {
            "credentials": [
              {
                "claim": {
                  "KYCValidated": true,
                  "id": "did:ixo:4XJLBfGtWSGKSz4BeRxdun"
                },
                "issued": "2020-07-20T16:17:25+02:00",
                "issuer": "did:ixo:UKzkhVSHc3qEFva5EY2XHt",
                "type": [
                  "Credential",
                  "ProofOfKYC"
                ]
              }
            ],
            "did": "did:ixo:4XJLBfGtWSGKSz4BeRxdun",
            "pubKey": "2vMHhssdhrBCRFiq9vj7TxGYDybW4yYdrYh9JG56RaAt"
          }
        },
        {
          "type": "did/BaseDidDoc",
          "value": {
            "credentials": null,
            "did": "did:ixo:U4tSpzzv91HHqWW1YmFkHJ",
            "pubKey": "FkeDue5it82taeheMprdaPrctfK3DeVV9NnEPYDgwwRG"
          }
        },
        {
          "type": "did/BaseDidDoc",
          "value": {
            "credentials": null,
            "did": "did:ixo:UKzkhVSHc3qEFva5EY2XHt",
            "pubKey": "Ftsqjc2pEvGLqBtgvVx69VXLe1dj2mFzoi4kqQNGo3Ej"
          }
        },
        {
          "type": "did/BaseDidDoc",
          "value": {
            "credentials": null,
            "did": "did:sov:CYCc2xaJKrp8Yt947Nc6jd",
            "pubKey": "7HjjYKd4SoBv26MqXp1SzmvDiouQxarBZ2ryscZLK22x"
          }
        },
        {
          "type": "did/BaseDidDoc",
          "value": {
            "credentials": null,
            "did": "did:sov:Q6UjNyxDLdm3kBxhGFnjrZ",
            "pubKey": "Db4YYVp1JVQNqicAhpdhpbbBggjdp1WKrZogMs5f7onn"
          }
        }
      ]
    },
    "distribution": {
      "base_proposer_reward": "0.010000000000000000",
      "bonus_proposer_reward": "0.040000000000000000",
      "community_tax": "0.020000000000000000",
      "delegator_starting_infos": [
        {
          "delegator_address": "ixo1z7vwqeku3sz34sd8eq4ppg9stkv8ugu959jy26",
          "starting_info": {
            "creation_height": "0",
            "previous_period": "1",
            "stake": "1000000.000000000000000000"
          },
          "validator_address": "ixovaloper1z7vwqeku3sz34sd8eq4ppg9stkv8ugu97yz4jl"
        }
      ],
      "delegator_withdraw_infos": [],
      "fee_pool": {
        "community_pool": [
          {
            "amount": "4351.000000000000000000",
            "denom": "uixo"
          }
        ]
      },
      "outstanding_rewards": [
        {
          "outstanding_rewards": null,
          "validator_address": "ixovaloper1z7vwqeku3sz34sd8eq4ppg9stkv8ugu97yz4jl"
        }
      ],
      "previous_proposer": "ixovalcons1zzm4an6wvt9frm5awvq7wl40cwp5n3ll6sfvw5",
      "validator_accumulated_commissions": [
        {
          "accumulated": null,
          "validator_address": "ixovaloper1z7vwqeku3sz34sd8eq4ppg9stkv8ugu97yz4jl"
        }
      ],
      "validator_current_rewards": [
        {
          "rewards": {
            "period": "2",
            "rewards": null
          },
          "validator_address": "ixovaloper1z7vwqeku3sz34sd8eq4ppg9stkv8ugu97yz4jl"
        }
      ],
      "validator_historical_rewards": [
        {
          "period": "1",
          "rewards": {
            "cumulative_reward_ratio": null,
            "reference_count": 2
          },
          "validator_address": "ixovaloper1z7vwqeku3sz34sd8eq4ppg9stkv8ugu97yz4jl"
        }
      ],
      "validator_slash_events": [],
      "withdraw_addr_enabled": true
    },
    "genutil": {
      "gentxs": null
    },
    "gov": {
      "deposit_params": {
        "max_deposit_period": "172800000000000",
        "min_deposit": [
          {
            "amount": "10000000",
            "denom": "uixo"
          }
        ]
      },
      "deposits": null,
      "proposals": [],
      "starting_proposal_id": "1",
      "tally_params": {
        "quorum": "0.334000000000000000",
        "threshold": "0.500000000000000000",
        "veto": "0.334000000000000000"
      },
      "votes": null,
      "voting_params": {
        "voting_period": "172800000000000"
      }
    },
    "mint": {
      "minter": {
        "annual_provisions": "83718698.854618250862186515",
        "inflation": "0.138375855286228915"
      },
      "params": {
        "blocks_per_year": "6311520",
        "goal_bonded": "0.670000000000000000",
        "inflation_max": "0.200000000000000000",
        "inflation_min": "0.070000000000000000",
        "inflation_rate_change": "0.130000000000000000",
        "mint_denom": "uixo"
      }
    },
    "oracles": {
      "oracles": [
        {
          "capabilities": [
            {
              "capabilities": [
                "mint"
              ],
              "denom": "uixo"
            }
          ],
          "oracle_did": "did:ixo:4XJLBfGtWSGKSz4BeRxdun"
        },
        {
          "capabilities": [
            {
              "capabilities": [
                "transfer"
              ],
              "denom": "res"
            },
            {
              "capabilities": [
                "transfer"
              ],
              "denom": "rez"
            }
          ],
          "oracle_did": "did:ixo:U4tSpzzv91HHqWW1YmFkHJ"
        },
        {
          "capabilities": [
            {
              "capabilities": [
                "mint",
                "burn",
                "transfer"
              ],
              "denom": "uixo"
            },
            {
              "capabilities": [
                "mint",
                "burn",
                "transfer"
              ],
              "denom": "xusd"
            }
          ],
          "oracle_did": "did:ixo:UKzkhVSHc3qEFva5EY2XHt"
        }
      ]
    },
    "payments": {
      "params": {
        "claim_fee_amount": "60000000.000000000000000000",
        "evaluation_agent_registration_fee_amount": "0.000000000000000000",
        "evaluation_fee_amount": "40000000.000000000000000000",
        "evaluation_pay_fee_percentage": "0.100000000000000000",
        "evaluation_pay_node_fee_percentage": "0.200000000000000000",
        "initiation_fee_amount": "50000000000.000000000000000000",
        "initiation_node_fee_percentage": "0.000000000000000000",
        "ixo_factor": "1.000000000000000000",
        "node_fee_percentage": "0.500000000000000000",
        "service_agent_registration_fee_amount": "0.000000000000000000"
      },
      "payment_contracts": null,
      "payment_templates": null,
      "subscriptions": null
    },
    "project": {
      "account_maps": [
        {
          "InitiatingNodePayFees": "ixo1h0yfg4hwr94hnjefqtt7gtx7kwf7t074zx7z2j",
          "IxoFees": "ixo1d6jhc4fkxfpfrj2am946rjwyzs3gr9f4a53rnt",
          "IxoPayFees": "ixo1y8d0vq2vdlcwkc69u56jm7mtq0ukmurldjhznm",
          "ValidatingNodeSetFees": "ixo145p7whcq5a7ryp08dnt6k2j6uta8uurta8tmtl",
          "did:ixo:7u8t5WsgBrbRo9USKo7Hhe": "ixo1s0vcxa7jh324aggczgtzs7vesnvtarpal4r55n"
        },
        {
          "InitiatingNodePayFees": "ixo1mc26j5u0mzezvn0y39vuh07y7zhcwk70lvw9f5",
          "IxoFees": "ixo14a93em9gcyw3j6ah5lxw2e9gr8y7g7armxq4vn",
          "IxoPayFees": "ixo102jkxgp6za7u5582q6ja6kn6j5t622rur9930e",
          "ValidatingNodeSetFees": "ixo1meqgeyxr0cvpe3lmajsvj89ahrl4qzqy9sa7hp",
          "did:ixo:9PQQyZhp5jzHzdjHHA1tJN": "ixo18sfltmqgw68xydhnd5r024xl2pk5anpyjann0a"
        },
        {
          "InitiatingNodePayFees": "ixo1uzyy4u5vmcq69r356ux2ay28rkqt3rmte7gp79",
          "IxoFees": "ixo1anflsj7xpnenlervqgneexwmnc89uq7kc45754",
          "IxoPayFees": "ixo1j6asna38vta9t4ugata64vvutwnwyuw28mwyqn",
          "ValidatingNodeSetFees": "ixo1eykltnkjph2vm90gqak57drwyehq5pypvsd7pm",
          "did:ixo:RUmPKi9yr25eZe25vHZzep": "ixo1zmxa64sj7e7zs5pfuavy83dxkzmfy3jk29h8ye"
        },
        {
          "InitiatingNodePayFees": "ixo1yq3jv9fvq9azpt6xsqlf3vnfcw32s8jtx57vjt",
          "IxoFees": "ixo1csetxz40p695pkt0rws5vw8z87lmphvq28wg5f",
          "IxoPayFees": "ixo1d59yugmejpt9h86qu0f7samaapxlk74fvfqhp6",
          "ValidatingNodeSetFees": "ixo1pcl6x7j39xcnzhrhp83ta335acxqpnaduxw383",
          "did:ixo:SHd1eLeN2gg3eWnNXLSvw4": "ixo16z8pc6jxelx00ep8jejxv4p8ee27k0w6ku4env"
        },
        {
          "InitiatingNodePayFees": "ixo168t3wrwl5tehj8pmhnv4wl76qagdtlcrf0lczn",
          "IxoFees": "ixo1jv59h24f2l4dc4uynpcz6nek6l4a3ph4w8gdel",
          "IxoPayFees": "ixo1lfsthzhftu6wdxcl3adtkagn378g8rcpn5u65a",
          "ValidatingNodeSetFees": "ixo1xhhrdefx005zc79hjptafsjnf70ud2ef2ylp4d",
          "did:ixo:U5mornGYGUnnLTG4n1sA7o": "ixo175l89h7ljfyh5l6xssqtlnfwyx26zvj7a7q5de"
        },
        {
          "InitiatingNodePayFees": "ixo1v22htx9j4vz0jxpun20nhl785mh0wcmatrrxku",
          "IxoFees": "ixo1kgdjfmy9xh53j35khxf7yhln9q57sch35dtxxe",
          "IxoPayFees": "ixo1f2p6nlkn0txhfj3pd6el5clfrvcpxsjdvyrd8y",
          "ValidatingNodeSetFees": "ixo1s9nshrjd968qg25phucwf98vg0krjh5vjvuhup",
          "did:ixo:XG7qNTbfKq93zepUHxYyiu": "ixo1cgxcumdjcsswldyjnuvgrau7526r5h2mnl2kw6"
        },
        {
          "InitiatingNodePayFees": "ixo1f7f6ntaqhh47gd34xh8q5dma5uq7dxufzmyxcl",
          "IxoFees": "ixo1v67krkrlxvj3sumghaqygftv7dprd4lx3sxmpq",
          "IxoPayFees": "ixo1djw3hrjwv66phfhtagywceru8qjy480r9ay0yz",
          "ValidatingNodeSetFees": "ixo18z5jl6ufalekv3sp4pkrqej0nxurszke29xwkm",
          "did:ixo:xn4YJ3YPneQHuPN45NYhX": "ixo1djwl96r7gqfx5h3njt8u6ezx5qqtx9k78yry3f"
        }
      ],
      "params": {
        "ixo_did": "did:ixo:U4tSpzzv91HHqWW1YmFkHJ",
        "project_minimum_initial_funding": "1"
      },
      "project_docs": [
        {
          "data": {
            "autoApprove": [
              ""
            ],
            "bondDid": "did:ixo:U7GK8p8rVhJMKhBVRCJJ8c",
            "createdBy": "did:sov:CYCc2xaJKrp8Yt947Nc6jd",
            "createdOn": "2020-07-21T09:58:53Z",
            "ddoTags": [
              {
                "category": "Cell Type",
                "tags": [
                  "Index",
                  "Incubator"
                ]
              },
              {
                "category": "SDG",
                "tags": [
                  "SDG17 - Partnerships for Goals"
                ]
              },
              {
                "category": "Stage",
                "tags": [
                  "Forming"
                ]
              },
              {
                "category": "location",
                "tags": [
                  "Global"
                ]
              }
            ],
            "entityType": "Cell",
            "evaluatorPayPerClaim": "100",
            "founder": {
              "countryOfOrigin": "LI",
              "email": "ixo@ixo.world",
              "logoLink": "https://pds_pandora.ixo.world/public/i57r5o2rbaekcvrmkij",
              "name": "ixo.world",
              "shortDescription": "The New World Impact Economy",
              "websiteURL": "https://ixo.world"
            },
            "imageLink": "bv606t2rutekcvrmkgp",
            "impactAction": "Cells Incubated",
            "longDescription": "",
            "nodeDid": "did:ixo:Sdjhti1ywgWgQJqtgYrGzJ",
            "ownerEmail": "ixo@ixo.world",
            "ownerName": "ixo.world",
            "pageContent": [
              {
                "media": {
                  "caption": "Incubating cells",
                  "link": "",
                  "text": "Cell nodes connect people cybernetically into small-word and global networks",
                  "type": "image"
                },
                "subText": "The cell incubator will bring founders together to launch the first 10 cells through ixo.world. This will demonstrate how cyber-cellular organisations operate. Each cell will have an impact mission and implement at least one project, with accountable targets. Up to 100 applications will be accepted for the first cohort. The top 10 candidates will be invited to join the incubator. The work of this incubator will be considered done only after at least 8 of the teams have achieved their cell recruitment and project performance targets. On successful completion, cells will be rewarded with an economic stake in the ixo.world relayer node, valued at 5,000 Euro.",
                "subTitle": "Mission",
                "text": "The Cell Incubator connects a network of teams who are founding their own cells to implement pilot projects through ixo.world. A cyber-cell is a highly networked, intelligent form of organisation. This enables people to achieve a shared mission through self-coordination, self-governance, sharing common resources and having access to the same sources of truth. Cells mimic how nature operates in ways that are decentralised, self-regulating and adaptive. The human immune system is a great example. This organisational model is popular with high-performing teams. Now we can virtualise and augment cellular orgranisations with cybernetic capabilites, so that they can sense and respond much more rapidly and precisely to changes in the world. Members of the incubator cell will support each other to learn about, develop and implement cybernetic tools for their use-cases, using artificial intelligence, blockchain smart contracts, p2p communications, electronic rights and decentralised finance mechanisms.",
                "title": "Incubating cells"
              }
            ],
            "projectLocation": "AA",
            "requiredClaims": "100",
            "sdgs": [],
            "serviceEndpoint": "https://pds_pandora.ixo.world/",
            "shortDescription": "Assisting you to organise with cyber-powers to achieve your mission.",
            "socialMedia": {
              "discourselink": "https://forum.ixo.world/c/cybercells",
              "facebookLink": "https://www.facebook.com/ixoworld",
              "githublink": "https://github.com/ixofoundation/cybercells",
              "instagramLink": "https://instagram.com/ixo.world",
              "telegramlink": "https://t.me/joinchat/cybercells",
              "twitterLink": "https://twitter.com/ixoworld",
              "webLink": "https://app.ixo.world//entities/select?type=Cell"
            },
            "templates": {
              "claim": {
                "form": "3yeywhcjbi8kcvrmke2",
                "schema": "i46diwv3i9kcvrmkiy"
              }
            },
            "title": "Cell Incubator"
          },
          "projectDid": "did:ixo:7u8t5WsgBrbRo9USKo7Hhe",
          "pubKey": "4m65rq7guxJ7UMGvNDAfjYd1WA4A76bELPmBAbUUNZCs",
          "senderDid": "did:sov:CYCc2xaJKrp8Yt947Nc6jd",
          "status": "CREATED",
          "txHash": "f382fc6614f312eac234d023b3f1120feb080b2caa22cdbd4b7e7652e4277a9d"
        },
        {
          "data": {
            "autoApprove": [
              ""
            ],
            "bondDid": "did:ixo:U7GK8p8rVhJMKhBVRCJJ8c",
            "createdBy": "did:sov:CYCc2xaJKrp8Yt947Nc6jd",
            "createdOn": "2020-07-20T16:34:59Z",
            "ddoTags": [
              {
                "category": "Cell Type",
                "tags": [
                  "Index",
                  "Civic Action",
                  "Covid-19",
                  "Epidemic Response",
                  "Immune Cell"
                ]
              },
              {
                "category": "SDG",
                "tags": [
                  "SDG17 - Partnerships for Goals"
                ]
              },
              {
                "category": "Stage",
                "tags": [
                  "Forming"
                ]
              },
              {
                "category": "location",
                "tags": [
                  "Global"
                ]
              }
            ],
            "entityType": "cell",
            "evaluatorPayPerClaim": "100",
            "founder": {
              "countryOfOrigin": "LI",
              "email": "ixo@ixo.world",
              "logoLink": "https://pds_pandora.ixo.world/public/r8rc7xbndrekcuqc2yq",
              "name": "ixo.world",
              "shortDescription": "The new world impact economy",
              "websiteURL": "https://ixo.world"
            },
            "imageLink": "rm1g3fi4gynkcuqc2yn",
            "impactAction": "Cells Formed",
            "longDescription": "Cellular organisations (Cells) are a highly effective coordination mechanism for people to self-organise and self-govern towards achieving a common mission. By definition, cells are decentralised, autonomous, locally responsive, adaptable, hyper-networked, intelligent and purpose-driven. They are highly suitable for virtual and remote teams to work together and share common resources. [Learn more](https://github.com/ixofoundation/docs/blob/master/ixo/concepts/cell-nodes/README.md) ",
            "nodeDid": "did:ixo:Sdjhti1ywgWgQJqtgYrGzJ",
            "ownerEmail": "ixo@ixo.world",
            "ownerName": "ixo.world",
            "pageContent": [
              {
                "media": {
                  "caption": "People form a Cell to pursue a shared mission",
                  "link": "https://pds_pandora.ixo.world/public/tketaxajq1bk9v3e9lw",
                  "text": "People form a Cell to pursue a shared mission",
                  "type": "image"
                },
                "subText": "Cell nodes are the digital infrastructure for all types of cellular organisations. These are decentralised, autonomous data stores with digital agency and cryptographic signing capabilities. Cell nodes enable data to be communicated quickly and securely through webs of trust. All participants in a cell have access to the same information and share intelligence both within their own cell node and with other organisations, through Internet of Impact networks.The digital artefacts created by a cell (such as Project Documents) are stored in the node as stateful records which are referenced in a distributed ledger. Public metadata are stored using the Interplanetary File System (IPFS). This allows cell nodes to retain a form of memory that can be stigmergically shared and rapidly amplified when cells need to be replicated or re-activated.",
                "subTitle": "Cell Nodes",
                "text": "Cellular organisations (Cells) are a highly effective coordination mechanism for people to self-organise and self-govern towards achieving a common mission. By definition, cells are decentralised, autonomous, locally responsive, adaptable, hyper-networked, intelligent and purpose-driven. They are highly suitable for virtual and remote teams to work together and share common resources.",
                "title": "Launch a Cellular Organisation"
              },
              {
                "media": {
                  "caption": "Test",
                  "link": "https://default.elysian.link/public/tix0bjytizljxxgfuka",
                  "type": "image"
                },
                "subText": "Primary education is typically the first stage of formal education, coming after preschool and before secondary school. Primary education takes place in primary school, the elementary school or first and middle school depending on the location.",
                "subTitle": "H2 In-Article Title",
                "text": "You think water moves fast? You should see ice. It moves like it has a mind. Like it knows it killed the world once and got a taste for murder.",
                "title": "Image In Article Section"
              },
              {
                "media": {
                  "link": "https://vimeo.com/264055837",
                  "type": "video"
                },
                "subText": "You think water moves fast? You should see ice. It moves like it has a mind. Like it knows it killed the world once and got a taste for murder. After the avalanche, it took us a week to climb out. Now, I don't know exactly when we turned on each other, but I know that seven of us survived the slide... and only five made it out. Now we took an oath, that I'm breaking now. We said we'd say it was the snow that killed the other two, but it wasn't. Nature is lethal but it doesn't hold a candle to man.",
                "subTitle": "H2 In-Article Title",
                "text": "The IXO foundation is undertaking a multi-year research program on innovative financing for improving primary school education. This project is part of a series of technology",
                "title": "Video Section"
              },
              {
                "table": {
                  "data": [
                    [
                      "xx XXX '20",
                      "Table Entry #1",
                      "Table Entry #2 With Longer Title",
                      "Table Entry #3",
                      "Table Entry #4"
                    ],
                    [
                      "xx XXX '20",
                      "Table Entry #1",
                      "Table Entry #2 With Longer Title",
                      "Table Entry #3",
                      "Table Entry #4"
                    ],
                    [
                      "xx XXX '20",
                      "Table Entry #1",
                      "Table Entry #2 With Longer Title",
                      "Table Entry #3",
                      "Table Entry #4"
                    ],
                    [
                      "xx XXX '20",
                      "Table Entry #1",
                      "Table Entry #2 With Longer Title",
                      "Table Entry #3",
                      "Table Entry #4"
                    ],
                    [
                      "xx XXX '20",
                      "Table Entry #1",
                      "Table Entry #2 With Longer Title",
                      "Table Entry #3",
                      "Table Entry #4"
                    ],
                    [
                      "xx XXX '20",
                      "Table Entry #1",
                      "Table Entry #2 With Longer Title",
                      "Table Entry #3",
                      "Table Entry #4"
                    ],
                    [
                      "xx XXX '20",
                      "Table Entry #1",
                      "Table Entry #2 With Longer Title",
                      "Table Entry #3",
                      "Table Entry #4"
                    ],
                    [
                      "xx XXX '20",
                      "Table Entry #1",
                      "Table Entry #2 With Longer Title",
                      "Table Entry #3",
                      "Table Entry #4"
                    ],
                    [
                      "xx XXX '20",
                      "Table Entry #1",
                      "Table Entry #2 With Longer Title",
                      "Table Entry #3",
                      "Table Entry #4"
                    ]
                  ],
                  "fields": [
                    "Date",
                    "Table Item 1",
                    "Table Item 2 With Long Title",
                    "Table Item 3 Med",
                    "Table Item 4"
                  ]
                },
                "title": "Table Section"
              },
              {
                "cards": [
                  {
                    "icons": [
                      {
                        "class": "twitter",
                        "url": "twitter.com/shaunbconway"
                      },
                      {
                        "class": "linkedin",
                        "url": "https://www.linkedin.com/in/drshaunconway/"
                      }
                    ],
                    "imageLink": "https://media-exp1.licdn.com/dms/image/C4E03AQFS3QKH0YvdOA/profile-displayphoto-shrink_200_200/0?e=1593648000\u0026v=beta\u0026t=-WUf1bFtDAR9Wsbguexto-v0q5RL9i_Np3c0FEovq2o",
                    "subtitle": "Co-Founder \u0026 CEO",
                    "title": "Joyce Montgomery"
                  },
                  {
                    "icons": [
                      {
                        "class": "twitter",
                        "url": "twitter.com/test"
                      },
                      {
                        "class": "linkedin",
                        "url": "https://www.linkedin.com/in/drshaunconway/"
                      }
                    ],
                    "imageLink": "https://media-exp1.licdn.com/dms/image/C4E03AQFS3QKH0YvdOA/profile-displayphoto-shrink_200_200/0?e=1593648000\u0026v=beta\u0026t=-WUf1bFtDAR9Wsbguexto-v0q5RL9i_Np3c0FEovq2o",
                    "subtitle": "CTO",
                    "title": "Islam Naidoo"
                  },
                  {
                    "icons": [
                      {
                        "class": "twitter",
                        "url": "twitter.com/test"
                      },
                      {
                        "class": "linkedin",
                        "url": "https://www.linkedin.com/in/drshaunconway/"
                      }
                    ],
                    "imageLink": "aaaa",
                    "subtitle": "Designer",
                    "title": "Jonathan Mike"
                  },
                  {
                    "icons": [
                      {
                        "class": "twitter",
                        "url": "twitter.com/test"
                      },
                      {
                        "class": "linkedin",
                        "url": "https://www.linkedin.com/in/drshaunconway/"
                      }
                    ],
                    "imageLink": "https://media-exp1.licdn.com/dms/image/C4E03AQFS3QKH0YvdOA/profile-displayphoto-shrink_200_200/0?e=1593648000\u0026v=beta\u0026t=-WUf1bFtDAR9Wsbguexto-v0q5RL9i_Np3c0FEovq2o",
                    "subtitle": "Co-Founder \u0026 CEO",
                    "title": "Daniel Ingram"
                  }
                ],
                "title": "Profile Card"
              }
            ],
            "projectLocation": "GL",
            "requiredClaims": "500",
            "sdgs": [],
            "serviceEndpoint": "https://pds_pandora.ixo.world/",
            "shortDescription": "Create your own Cell with an impact mission.",
            "socialMedia": {
              "discourselink": "https://forum.ixo.world/c/c19",
              "facebookLink": "https://www.facebook.com/ixoworld",
              "githublink": "https://github.com/ixofoundation/c19",
              "instagramLink": "https://instagram.com/ixo.world",
              "telegramlink": "https://t.me/joinchat/c19cells",
              "twitterLink": "https://twitter.com/c19cells",
              "webLink": "https://c19.ixo.world"
            },
            "templates": {
              "claim": {
                "form": "o9l11mocmlkcuqc2vm",
                "schema": "ygqer2bskvakcuqc2t4"
              }
            },
            "title": "Cellular Organisations"
          },
          "projectDid": "did:ixo:9PQQyZhp5jzHzdjHHA1tJN",
          "pubKey": "5a7BPk3nYfwL7J89GBPT7hmcKFGgkGvH8C9qP8iNYp72",
          "senderDid": "did:sov:CYCc2xaJKrp8Yt947Nc6jd",
          "status": "CREATED",
          "txHash": "7474ce6ee5842a71e0aefeb49c0138c823e8c95c61ee60c49b58d3a7bf291ce4"
        },
        {
          "data": {
            "autoApprove": [
              "SA"
            ],
            "bondDid": "did:ixo:U7GK8p8rVhJMKhBVRCJJ8c",
            "createdBy": "did:sov:CYCc2xaJKrp8Yt947Nc6jd",
            "createdOn": "2020-07-20T16:20:23Z",
            "ddoTags": [
              {
                "category": "project type",
                "tags": [
                  "index",
                  "featured",
                  "social finance"
                ]
              },
              {
                "category": "stage",
                "tags": [
                  "planning"
                ]
              }
            ],
            "entityType": "project",
            "evaluatorPayPerClaim": "15",
            "founder": {
              "countryOfOrigin": "SW",
              "email": "info@ixo.foundation",
              "logoLink": "https://pds_pandora.ixo.world/public/e1hvxv6kplgkcuptbue",
              "name": "ixo Foundation",
              "shortDescription": "The ixo foundation researches and develops open-source protocols for sustainable development",
              "websiteURL": "https://ixo.foundation/"
            },
            "imageLink": "qqexy2nayhkcuptbw0",
            "impactAction": "Academic Pass",
            "longDescription": "",
            "nodeDid": "did:ixo:Sdjhti1ywgWgQJqtgYrGzJ",
            "ownerEmail": "info@ixo.foundation",
            "ownerName": "ixo Foundation",
            "pageContent": [
              {
                "media": {
                  "caption": "Funding the transition to technology-enabled education",
                  "link": "https://pds_pandora.ixo.world/public/qtcfdv29bygkbv0g3ey",
                  "text": "Alpha-bonds are an innovation for funding access to educational technologies",
                  "type": "image"
                },
                "subText": "The ixo foundation is undertaking a multi-year research program on innovative financing to rapidly scale proven interventions that improve the quality of primary education. This project is part of a series of technology experiments using the ixo protocol and alpha-bonds.",
                "subTitle": "Research Objective",
                "text": "India has made enormous progress in education to achieve a 99% rate of primary school access. The Sustainable Development Goals have now focused attention on improving the quality of education to ensure that children in school are actually learning. A typical student in India is at least two grades behind the level expected for their age in literacy and numeracy. The Quality Education India Development Impact Bond (DIB) programme supports Indian education providers to improve learning outcomes for primary school children through an innovative results-based funding mechanism.",
                "title": "Development Impact Bonds for Education"
              }
            ],
            "projectLocation": "IN",
            "requiredClaims": "50",
            "sdgs": [
              3,
              11
            ],
            "serviceEndpoint": "https://pds_pandora.ixo.world/",
            "shortDescription": "Innovative financing for scaling learning outcomes from quality primary education programmes.",
            "socialMedia": {
              "discourselink": "http://forum.ixo.world",
              "githublink": "https://github.com/ixofoundation",
              "instagramLink": "",
              "linkedInLink": "",
              "telegramlink": "https://t.me/ixonetwork",
              "twitterLink": "https://twitter.com/ixoworld",
              "webLink": "https://ixo.foundation"
            },
            "templates": {
              "claim": {
                "form": "i6z7hu1mqkkcuptbfm",
                "schema": "k5npdd35o3akcuptbw6"
              }
            },
            "title": "Quality Primary Education"
          },
          "projectDid": "did:ixo:RUmPKi9yr25eZe25vHZzep",
          "pubKey": "ELpaZcnvQD16Ckt6G9hY88temmz89AqyBxo2myPjbRmm",
          "senderDid": "did:sov:CYCc2xaJKrp8Yt947Nc6jd",
          "status": "CREATED",
          "txHash": "e93356dd75658701026e6218314db74b3424c2eeb0743bfcea88ff57a45391e9"
        },
        {
          "data": {
            "autoApprove": [
              "SA"
            ],
            "bondDid": "did:ixo:U7GK8p8rVhJMKhBVRCJJ8c",
            "createdBy": "did:sov:CYCc2xaJKrp8Yt947Nc6jd",
            "createdOn": "2020-07-20T21:21:53Z",
            "ddoTags": [
              {
                "category": "project type",
                "tags": [
                  "index",
                  "featured",
                  "social finance"
                ]
              },
              {
                "category": "stage",
                "tags": [
                  "planning"
                ]
              }
            ],
            "entityType": "project",
            "evaluatorPayPerClaim": "15",
            "founder": {
              "countryOfOrigin": "SW",
              "email": "info@ixo.foundation",
              "logoLink": "https://pds_pandora.ixo.world/public/3ygaazabzvfkcv0l187",
              "name": "ixo Foundation",
              "shortDescription": "The ixo foundation researches and develops open-source protocols for sustainable development",
              "websiteURL": "https://ixo.foundation/"
            },
            "imageLink": "db08b0fz54jkcv0l191",
            "impactAction": "Academic Pass",
            "longDescription": "",
            "nodeDid": "did:ixo:Sdjhti1ywgWgQJqtgYrGzJ",
            "ownerEmail": "info@ixo.foundation",
            "ownerName": "ixo Foundation",
            "pageContent": [
              {
                "media": {
                  "caption": "Funding the transition to technology-enabled education",
                  "link": "https://pds_pandora.ixo.world/public/qtcfdv29bygkbv0g3ey",
                  "text": "Alpha-bonds are an innovation for funding access to educational technologies",
                  "type": "image"
                },
                "subText": "The ixo foundation is undertaking a multi-year research program on innovative financing to rapidly scale proven interventions that improve the quality of primary education. This project is part of a series of technology experiments using the ixo protocol and alpha-bonds.",
                "subTitle": "Research Objective",
                "text": "India has made enormous progress in education to achieve a 99% rate of primary school access. The Sustainable Development Goals have now focused attention on improving the quality of education to ensure that children in school are actually learning. A typical student in India is at least two grades behind the level expected for their age in literacy and numeracy. The Quality Education India Development Impact Bond (DIB) programme supports Indian education providers to improve learning outcomes for primary school children through an innovative results-based funding mechanism.",
                "title": "Development Impact Bonds for Education"
              }
            ],
            "projectLocation": "IN",
            "requiredClaims": "50",
            "sdgs": [
              3,
              11
            ],
            "serviceEndpoint": "https://pds_pandora.ixo.world/",
            "shortDescription": "Innovative financing for scaling learning outcomes from quality primary education programmes.",
            "socialMedia": {
              "discourselink": "http://forum.ixo.world",
              "githublink": "https://github.com/ixofoundation",
              "instagramLink": "",
              "linkedInLink": "",
              "telegramlink": "https://t.me/ixonetwork",
              "twitterLink": "https://twitter.com/ixoworld",
              "webLink": "https://ixo.foundation"
            },
            "templates": {
              "claim": {
                "form": "u697r6rr63jkcv0l1ad",
                "schema": "ms7p6ydfrxqkcv0l1b7"
              }
            },
            "title": "Quality Primary Education"
          },
          "projectDid": "did:ixo:SHd1eLeN2gg3eWnNXLSvw4",
          "pubKey": "EnMn5vd2ViZTFuMkqGf9AYhQKgcnegJHVHXrH5iyopdy",
          "senderDid": "did:sov:CYCc2xaJKrp8Yt947Nc6jd",
          "status": "CREATED",
          "txHash": "96ce22904d0c1d8f418e919d71f211a70de49a0d2e13c7b97ae8028bdd08be8e"
        },
        {
          "data": {
            "autoApprove": [
              "SA"
            ],
            "bondDid": "did:ixo:U7GK8p8rVhJMKhBVRCJJ8c",
            "createdBy": "did:sov:CYCc2xaJKrp8Yt947Nc6jd",
            "createdOn": "2020-07-20T20:14:16Z",
            "ddoTags": [
              {
                "category": "project type",
                "tags": [
                  "index",
                  "featured",
                  "social finance"
                ]
              },
              {
                "category": "stage",
                "tags": [
                  "planning"
                ]
              }
            ],
            "entityType": "project",
            "evaluatorPayPerClaim": "15",
            "founder": {
              "countryOfOrigin": "SW",
              "email": "info@ixo.foundation",
              "logoLink": "https://pds_pandora.ixo.world/public/o8w9ttsieykcuy60a5",
              "name": "ixo Foundation",
              "shortDescription": "The ixo foundation researches and develops open-source protocols for sustainable development",
              "websiteURL": "https://ixo.foundation/"
            },
            "imageLink": "owtcdmj17kcuy60nf",
            "impactAction": "Academic Pass",
            "longDescription": "",
            "nodeDid": "did:ixo:Sdjhti1ywgWgQJqtgYrGzJ",
            "ownerEmail": "info@ixo.foundation",
            "ownerName": "ixo Foundation",
            "pageContent": [
              {
                "media": {
                  "caption": "Funding the transition to technology-enabled education",
                  "link": "https://pds_pandora.ixo.world/public/qtcfdv29bygkbv0g3ey",
                  "text": "Alpha-bonds are an innovation for funding access to educational technologies",
                  "type": "image"
                },
                "subText": "The ixo foundation is undertaking a multi-year research program on innovative financing to rapidly scale proven interventions that improve the quality of primary education. This project is part of a series of technology experiments using the ixo protocol and alpha-bonds.",
                "subTitle": "Research Objective",
                "text": "India has made enormous progress in education to achieve a 99% rate of primary school access. The Sustainable Development Goals have now focused attention on improving the quality of education to ensure that children in school are actually learning. A typical student in India is at least two grades behind the level expected for their age in literacy and numeracy. The Quality Education India Development Impact Bond (DIB) programme supports Indian education providers to improve learning outcomes for primary school children through an innovative results-based funding mechanism.",
                "title": "Development Impact Bonds for Education"
              }
            ],
            "projectLocation": "IN",
            "requiredClaims": "50",
            "sdgs": [
              3,
              11
            ],
            "serviceEndpoint": "https://pds_pandora.ixo.world/",
            "shortDescription": "Innovative financing for scaling learning outcomes from quality primary education programmes.",
            "socialMedia": {
              "discourselink": "http://forum.ixo.world",
              "githublink": "https://github.com/ixofoundation",
              "instagramLink": "",
              "linkedInLink": "",
              "telegramlink": "https://t.me/ixonetwork",
              "twitterLink": "https://twitter.com/ixoworld",
              "webLink": "https://ixo.foundation"
            },
            "templates": {
              "claim": {
                "form": "iwzwo1zmokkcuy60b9",
                "schema": "bj52ioh9g6ekcuy60nr"
              }
            },
            "title": "Quality Primary Education"
          },
          "projectDid": "did:ixo:U5mornGYGUnnLTG4n1sA7o",
          "pubKey": "Fm8Dag1Q2HhdsdyZyrTHKsrsWdvcsagbLbrg4Jw9MiFW",
          "senderDid": "did:sov:CYCc2xaJKrp8Yt947Nc6jd",
          "status": "CREATED",
          "txHash": "a94dc06e48ff903fb36a3ebe54433ec27a17a7e0e93529c896abeb21c2604a71"
        },
        {
          "data": {
            "autoApprove": [
              "SA"
            ],
            "bondDid": "did:ixo:U7GK8p8rVhJMKhBVRCJJ8c",
            "createdBy": "did:sov:CYCc2xaJKrp8Yt947Nc6jd",
            "createdOn": "2020-07-20T16:18:44Z",
            "ddoTags": [
              {
                "category": "project type",
                "tags": [
                  "index",
                  "featured",
                  "social finance"
                ]
              },
              {
                "category": "stage",
                "tags": [
                  "planning"
                ]
              }
            ],
            "entityType": "project",
            "evaluatorPayPerClaim": "15",
            "founder": {
              "countryOfOrigin": "SW",
              "email": "info@ixo.foundation",
              "logoLink": "https://pds_pandora.ixo.world/public/erlji5nzp0tkcupqwao",
              "name": "ixo Foundation",
              "shortDescription": "The ixo foundation researches and develops open-source protocols for sustainable development",
              "websiteURL": "https://ixo.foundation/"
            },
            "imageLink": "xr2x7bom5kcupqwc8",
            "impactAction": "Academic Pass",
            "longDescription": "",
            "nodeDid": "did:ixo:Sdjhti1ywgWgQJqtgYrGzJ",
            "ownerEmail": "info@ixo.foundation",
            "ownerName": "ixo Foundation",
            "pageContent": [
              {
                "media": {
                  "caption": "Funding the transition to technology-enabled education",
                  "link": "https://pds_pandora.ixo.world/public/qtcfdv29bygkbv0g3ey",
                  "text": "Alpha-bonds are an innovation for funding access to educational technologies",
                  "type": "image"
                },
                "subText": "The ixo foundation is undertaking a multi-year research program on innovative financing to rapidly scale proven interventions that improve the quality of primary education. This project is part of a series of technology experiments using the ixo protocol and alpha-bonds.",
                "subTitle": "Research Objective",
                "text": "India has made enormous progress in education to achieve a 99% rate of primary school access. The Sustainable Development Goals have now focused attention on improving the quality of education to ensure that children in school are actually learning. A typical student in India is at least two grades behind the level expected for their age in literacy and numeracy. The Quality Education India Development Impact Bond (DIB) programme supports Indian education providers to improve learning outcomes for primary school children through an innovative results-based funding mechanism.",
                "title": "Development Impact Bonds for Education"
              }
            ],
            "projectLocation": "IN",
            "requiredClaims": "50",
            "sdgs": [
              3,
              11
            ],
            "serviceEndpoint": "https://pds_pandora.ixo.world/",
            "shortDescription": "Innovative financing for scaling learning outcomes from quality primary education programmes.",
            "socialMedia": {
              "discourselink": "http://forum.ixo.world",
              "githublink": "https://github.com/ixofoundation",
              "instagramLink": "",
              "linkedInLink": "",
              "telegramlink": "https://t.me/ixonetwork",
              "twitterLink": "https://twitter.com/ixoworld",
              "webLink": "https://ixo.foundation"
            },
            "templates": {
              "claim": {
                "form": "pdhrt89s1utkcupqwb8",
                "schema": "azsiu3fqqafkcupqw9t"
              }
            },
            "title": "Quality Primary Education"
          },
          "projectDid": "did:ixo:XG7qNTbfKq93zepUHxYyiu",
          "pubKey": "HVbjbwyd1u24oo9nTVG4qFxQLK1TGPMmnEmy6otukw2D",
          "senderDid": "did:sov:CYCc2xaJKrp8Yt947Nc6jd",
          "status": "CREATED",
          "txHash": "85d3f3f1dbc224feee02aa5feb151c03285cbd368424fc29f726a2646fe08705"
        },
        {
          "data": {
            "autoApprove": [
              "SA"
            ],
            "bondDid": "did:ixo:U7GK8p8rVhJMKhBVRCJJ8c",
            "createdBy": "did:sov:CYCc2xaJKrp8Yt947Nc6jd",
            "createdOn": "2020-07-20T20:04:28Z",
            "ddoTags": [
              {
                "category": "project type",
                "tags": [
                  "index",
                  "featured",
                  "social finance"
                ]
              },
              {
                "category": "stage",
                "tags": [
                  "planning"
                ]
              }
            ],
            "entityType": "project",
            "evaluatorPayPerClaim": "15",
            "founder": {
              "countryOfOrigin": "SW",
              "email": "info@ixo.foundation",
              "logoLink": "https://pds_pandora.ixo.world/public/4ifjgtqscjbkcuxt963",
              "name": "ixo Foundation",
              "shortDescription": "The ixo foundation researches and develops open-source protocols for sustainable development",
              "websiteURL": "https://ixo.foundation/"
            },
            "imageLink": "4741v5hergskcuxt9bc",
            "impactAction": "Academic Pass",
            "longDescription": "",
            "nodeDid": "did:ixo:Sdjhti1ywgWgQJqtgYrGzJ",
            "ownerEmail": "info@ixo.foundation",
            "ownerName": "ixo Foundation",
            "pageContent": [
              {
                "media": {
                  "caption": "Funding the transition to technology-enabled education",
                  "link": "https://pds_pandora.ixo.world/public/qtcfdv29bygkbv0g3ey",
                  "text": "Alpha-bonds are an innovation for funding access to educational technologies",
                  "type": "image"
                },
                "subText": "The ixo foundation is undertaking a multi-year research program on innovative financing to rapidly scale proven interventions that improve the quality of primary education. This project is part of a series of technology experiments using the ixo protocol and alpha-bonds.",
                "subTitle": "Research Objective",
                "text": "India has made enormous progress in education to achieve a 99% rate of primary school access. The Sustainable Development Goals have now focused attention on improving the quality of education to ensure that children in school are actually learning. A typical student in India is at least two grades behind the level expected for their age in literacy and numeracy. The Quality Education India Development Impact Bond (DIB) programme supports Indian education providers to improve learning outcomes for primary school children through an innovative results-based funding mechanism.",
                "title": "Development Impact Bonds for Education"
              }
            ],
            "projectLocation": "IN",
            "requiredClaims": "50",
            "sdgs": [
              3,
              11
            ],
            "serviceEndpoint": "https://pds_pandora.ixo.world/",
            "shortDescription": "Innovative financing for scaling learning outcomes from quality primary education programmes.",
            "socialMedia": {
              "discourselink": "http://forum.ixo.world",
              "githublink": "https://github.com/ixofoundation",
              "instagramLink": "",
              "linkedInLink": "",
              "telegramlink": "https://t.me/ixonetwork",
              "twitterLink": "https://twitter.com/ixoworld",
              "webLink": "https://ixo.foundation"
            },
            "templates": {
              "claim": {
                "form": "0kylgpkd5o5gkcuxt93w",
                "schema": "evgxd8ygrj7kcuxt971"
              }
            },
            "title": "Quality Primary Education"
          },
          "projectDid": "did:ixo:xn4YJ3YPneQHuPN45NYhX",
          "pubKey": "XQDf5qYVUFHHwL6YXvvpV38p1mhj9atZq9Hg6B2Mz8R",
          "senderDid": "did:sov:CYCc2xaJKrp8Yt947Nc6jd",
          "status": "CREATED",
          "txHash": "7a4f007fa84cb0321ddb0baf69467f6916c622c0eca3387856cad3f5941d3306"
        }
      ],
      "withdrawal_infos": [
        null,
        null,
        null,
        null,
        null,
        null,
        null
      ]
    },
    "slashing": {
      "missed_blocks": {
        "ixovalcons1zzm4an6wvt9frm5awvq7wl40cwp5n3ll6sfvw5": []
      },
      "params": {
        "downtime_jail_duration": "600000000000",
        "max_evidence_age": "120000000000",
        "min_signed_per_window": "0.500000000000000000",
        "signed_blocks_window": "100",
        "slash_fraction_double_sign": "0.050000000000000000",
        "slash_fraction_downtime": "0.010000000000000000"
      },
      "signing_infos": {
        "ixovalcons1zzm4an6wvt9frm5awvq7wl40cwp5n3ll6sfvw5": {
          "address": "ixovalcons1zzm4an6wvt9frm5awvq7wl40cwp5n3ll6sfvw5",
          "index_offset": "407658",
          "jailed_until": "1970-01-01T00:00:00Z",
          "missed_blocks_counter": "0",
          "start_height": "0",
          "tombstoned": false
        }
      }
    },
    "staking": {
      "delegations": [
        {
          "delegator_address": "ixo1z7vwqeku3sz34sd8eq4ppg9stkv8ugu959jy26",
          "shares": "1000000.000000000000000000",
          "validator_address": "ixovaloper1z7vwqeku3sz34sd8eq4ppg9stkv8ugu97yz4jl"
        }
      ],
      "exported": true,
      "last_total_power": "1",
      "last_validator_powers": [
        {
          "Address": "ixovaloper1z7vwqeku3sz34sd8eq4ppg9stkv8ugu97yz4jl",
          "Power": "1"
        }
      ],
      "params": {
        "bond_denom": "uixo",
        "max_entries": 7,
        "max_validators": 100,
        "unbonding_time": "1814400000000000"
      },
      "redelegations": null,
      "unbonding_delegations": null,
      "validators": [
        {
          "commission": {
            "commission_rates": {
              "max_change_rate": "0.010000000000000000",
              "max_rate": "0.200000000000000000",
              "rate": "0.100000000000000000"
            },
            "update_time": "2020-07-20T13:14:12.450422411Z"
          },
          "consensus_pubkey": "ixovalconspub1zcjduepq4m8e9akmyq4wrz003rd8puss84wzzelzqnte76gycqcvaahnd0pqte0wnj",
          "delegator_shares": "1000000.000000000000000000",
          "description": {
            "details": "",
            "identity": "",
            "moniker": "ixo-testnet-validator-nl",
            "website": ""
          },
          "jailed": false,
          "min_self_delegation": "1",
          "operator_address": "ixovaloper1z7vwqeku3sz34sd8eq4ppg9stkv8ugu97yz4jl",
          "status": 2,
          "tokens": "1000000",
          "unbonding_height": "0",
          "unbonding_time": "1970-01-01T00:00:00Z"
        }
      ]
    },
    "supply": {
      "supply": [
        {
          "amount": "6000000",
          "denom": "res"
        },
        {
          "amount": "6000000",
          "denom": "rez"
        },
        {
          "amount": "7",
          "denom": "token1"
        },
        {
          "amount": "10",
          "denom": "token2"
        },
        {
          "amount": "5",
          "denom": "token3"
        },
        {
          "amount": "5",
          "denom": "token4"
        },
        {
          "amount": "600001000000",
          "denom": "uixo"
        },
        {
          "amount": "5000000000",
          "denom": "xusd"
        }
      ]
    },
    "treasury": null
  }
}
